cloudfn/__init__.py
cloudfn/cli.py
cloudfn/django_handler.py
cloudfn/flask_handler.py
cloudfn/google_account.py
cloudfn/http.py
cloudfn/pubsub.py
cloudfn/storage.py
cloudfn/wsgi_util.py
cloudfn/docker/DockerfilePython2-7
cloudfn/docker/DockerfilePython3-5
cloudfn/docker/DockerfilePython3-5-alt
cloudfn/hooks/hook-django.contrib.py
cloudfn/hooks/hook-google.cloud.bigquery.py
cloudfn/hooks/hook-google.cloud.bigtable.py
cloudfn/hooks/hook-google.cloud.core.py
cloudfn/hooks/hook-google.cloud.datastore.py
cloudfn/hooks/hook-google.cloud.dns.py
cloudfn/hooks/hook-google.cloud.error_reporting.py
cloudfn/hooks/hook-google.cloud.firestore.py
cloudfn/hooks/hook-google.cloud.language.py
cloudfn/hooks/hook-google.cloud.logging.py
cloudfn/hooks/hook-google.cloud.monitoring.py
cloudfn/hooks/hook-google.cloud.pubsub.py
cloudfn/hooks/hook-google.cloud.resource_manager.py
cloudfn/hooks/hook-google.cloud.runtimeconfig.py
cloudfn/hooks/hook-google.cloud.spanner.py
cloudfn/hooks/hook-google.cloud.speech.py
cloudfn/hooks/hook-google.cloud.storage.py
cloudfn/hooks/hook-google.cloud.translate.py
cloudfn/hooks/hook-google.cloud.vision.py
cloudfn/hooks/hook-google.gax.py
cloudfn/hooks/hook-grpc.py
cloudfn/hooks/hook-rest_framework.py
cloudfn/hooks/hooks-django.middleware.py
cloudfn/hooks/unbuffered.py
cloudfn/template/index.js
pycloudfn-0.1.209.dist-info/DESCRIPTION.rst
pycloudfn-0.1.209.dist-info/METADATA
pycloudfn-0.1.209.dist-info/RECORD
pycloudfn-0.1.209.dist-info/WHEEL
pycloudfn-0.1.209.dist-info/entry_points.txt
pycloudfn-0.1.209.dist-info/metadata.json
pycloudfn-0.1.209.dist-info/top_level.txt
