Metadata-Version: 2.0
Name: pycloudfn
Version: 0.1.209
Summary: GCP Cloud functions in python
Home-page: https://github.com/MartinSahlen/cloud-functions-python
Author: Martin Sahlen
Author-email: martin8900@gmail.com
License: MIT
Platform: UNKNOWN
Classifier: Development Status :: 3 - Alpha
Classifier: Intended Audience :: Developers
Classifier: License :: OSI Approved :: MIT License
Classifier: Programming Language :: Python :: 2
Classifier: Programming Language :: Python :: 2.7
Classifier: Programming Language :: Python :: 3
Classifier: Programming Language :: Python :: 3.5
Requires-Dist: pyinstaller (==3.3.1)
Requires-Dist: python-dateutil (==2.6.0)
Requires-Dist: werkzeug (==0.12)
Requires-Dist: django (==1.11.1)
Requires-Dist: six (==1.10.0)
Requires-Dist: Jinja2 (==2.9.6)
Requires-Dist: pyspin (==1.1.1)
Requires-Dist: google-auth (==1.3.0)
